AUTHORS
CHANGES
COPYING.GPLv3
COPYING.LGPLv3
INSTALL
LICENSE
README
ez_setup.py
requirements.txt
setup.py
bin/draw_models.sh
bin/merengue-admin.py
conf/nginx/conf/nginx.conf
conf/scripts/merengue
conf/scripts/nginxctl
conf/scripts/update
docs/Makefile
docs/conf.py
docs/contents.txt
docs/index.txt
docs/_ext/applyxrefs.py
docs/_ext/literals_to_xrefs.py
docs/_ext/merenguedocs.py
docs/_static/basecontent_models.png
docs/_static/multimedia_models.png
docs/_static/permission_models.png
docs/_static/registry_models.png
docs/_static/section_models.png
docs/_theme/merenguedocs/genindex.html
docs/_theme/merenguedocs/layout.html
docs/_theme/merenguedocs/modindex.html
docs/_theme/merenguedocs/search.html
docs/_theme/merenguedocs/theme.conf
docs/_theme/merenguedocs/static/default.css
docs/_theme/merenguedocs/static/doc_bg.png
docs/_theme/merenguedocs/static/docicons-behindscenes.png
docs/_theme/merenguedocs/static/docicons-note.png
docs/_theme/merenguedocs/static/docicons-philosophy.png
docs/_theme/merenguedocs/static/homepage.css
docs/_theme/merenguedocs/static/inner_logo.jpg
docs/_theme/merenguedocs/static/merengue_bg.jpg
docs/_theme/merenguedocs/static/merenguedocs.css
docs/_theme/merenguedocs/static/reset-fonts-grids.css
docs/_theme/merenguedocs/static/skel_screenshot.png
docs/_theme/merenguedocs/static/skel_small_screenshot.png
docs/intro/index.txt
docs/intro/overview.txt
docs/intro/tutorial.txt
docs/intro/_images/block_reordering.png
docs/intro/_images/collaborative_edition.png
docs/intro/_images/content_creation.png
docs/intro/_images/merengue_theme_in_new_project.png
docs/intro/_images/merengueproject_admin_with_features.png
docs/intro/_images/merengueproject_features_admin.png
docs/intro/_images/merengueprojectorg_after_finishing_features_block.png
docs/intro/_images/merengueprojectorg_after_finishing_theme.png
docs/intro/_images/merengueprojectorg_blocks_admin.png
docs/intro/_images/merengueprojectorg_features_block.png
merengue.egg-info/PKG-INFO
merengue.egg-info/SOURCES.txt
merengue.egg-info/dependency_links.txt
merengue.egg-info/requires.txt
merengue.egg-info/top_level.txt
