Metadata-Version: 1.0
Name: merengue
Version: 0.9.0
Summary: Django-based CMS on steroids
Home-page: http://www.merengueproject.org/
Author: Yaco Sistemas
Author-email: msaelices@yaco.es
License: UNKNOWN
Keywords: merengue,django,django cms,pluggable,cms,collaborative edition,geolocation,translatable models
Platform: UNKNOWN
Classifier: Framework :: Django
Classifier: Intended Audience :: Developers
Classifier: License :: OSI Approved :: GNU Library or Lesser General Public License (LGPL)
Classifier: Operating System :: OS Independent
Classifier: Topic :: Internet :: WWW/HTTP
Classifier: Topic :: Internet :: WWW/HTTP :: WSGI
Classifier: Topic :: Internet :: WWW/HTTP :: Dynamic Content
Classifier: Topic :: Software Development :: Libraries :: Application Frameworks
Classifier: Topic :: Software Development :: Libraries :: Python Modules
Classifier: Environment :: Web Environment
Classifier: Programming Language :: Python
